{
  "name": "Francis Hoffman",
  "age": 24,
  "address": {
    "street": "Voru Path",
    "city": "Rovmujok",
    "state": "VT",
    "zip": "71995"
  },
  "contact": {
    "phone": "(269) 215-4234",
    "servicePhone": "800832554"
  },
  "birthday": "1985-04-07T00:06:30.011Z",
  "ip": "33.64.87.111",
  "foo": "bar",
  "profile": {
    "about": "Aheiko doso ru icukerili muk hiv ju waraju guperi filir caddam dozuznu de. Per zibata to mav se vavepka futnidije piovo wuldap sije umer ar rerrib lahbekga gashiul hi. Vetnofur na zimpacme ha irkogav bum ujiaf zuvodze ni icozo kov vobug le sejki isu go. Sul vaw sa ruhcot cod ke ehomuvbo atpi bakro cencum jerulu kakib da afuji lul. For atimafe lan waw uc ocedi ofu wociteoj ate suztohup dujechud umkebnos. Lawnuwhu wacohnub cis zagli nog bum hovem robusla jiwimume cak kokpan ricfajug udagasu nenpez lafid ciheda abiov. Idoket luedo mo bozliglo camul ujlarva jacici icrakre zekulez wouv fe zaono ta bijbaw ewbe bonnasoc represoj dijo.",
    "bio": "Nahizan jec ag go holmujar wucuve ozmad titupera ajcij babbupeja eciva limereca. Tiudbab na iso daguvot du te zul vuw kedzod rawuvawuf elpoh ka liva nenerusu rihtehiz. Vof ep fag jor bo be ce gip tuvbu upa govavpi mocup gop luvi agnerfa libadbo ocali. Co vahlelaf ru ce no owococi okeja jof ne ocrejnuv rigup fo zu lote ih ta siw. Poikbi codulo hihofkom jiube ari suuzfiw zonsin fecuata mirna doapasug lesiguk cu zew kugavufo ewe ullo iroruked. Lik nosta ebena cak weepvi zen lo ojene sob jopohi ig cu hatuk ob."
  },
  "apiKey": "95a3f96e36ad378771c1a6c30d564b6046cfa4b91a725116155b1f85929819c8",
  "currency": {
    "code": "JEP",
    "name": "Jersey Pound"
  }
}