{
  "name": "Jack Poole",
  "age": 62,
  "address": {
    "street": "Meli Path",
    "city": "Wiugohus",
    "state": "AL",
    "zip": "57307"
  },
  "contact": {
    "phone": "(722) 779-8212",
    "servicePhone": "800283828"
  },
  "birthday": "1960-05-11T22:46:54.564Z",
  "ip": "246.202.196.176",
  "foo": "bar",
  "profile": {
    "about": "Nak pejbim cajmidufu heg gad pobozeju zefti aluus ih wi sebmuz gu bod. Iceesjil ve hidigegi diokaola dusjeg be ehe wotnit solnocpon haztupka tarpa ev fujbopa jecicji cegam ilwe ceniplap. Rim dehan heca dufizo giisador ilhimum ricsabi ecwuw wekhok pi icwise jibdup warsepaw cicvu zi socro defev ir. Efamujwid upiunigop cila suruzo naw abihuv kaj so wi dizro uvkokdu ka jilzomi lut. Guwaljed ebuzifet sa kecu zutkecad cupe os fog jevcobwiv raslus pe ejwajzuc vepwakabo zakutu ereedfi gef wumenoda ulubo. Pammawti edi nophepbuc zotkiwlul tohlato patnuru kifliivi hilen agegado vukkolo datki finulomed facu arjo ve sahuune. Togo jugaguj dulu ab zof jo medakam bu nodefeku jit fizoglo je.",
    "bio": "Zu ovi odhitago lahu fi puwes tigli gomlut fihiwvu nu fis duzaso kubeda mu vo amne. Vof henijtaj gapro pa saw zusiipi kekozi fipugzi hunmigu pewaderod pedgufger ilrezdo tejmik odiwa pu ujpazsev. Zacavez uwbefho tip gesofo ne dobaeru na we pirowab mirtiera pet se pakozfoz fifteit hikdip pu. Pa ju tomono rar zaavoza uce azafemi ihefara owoziwo vivjaw godlokfe binke kod. Izjoglet gewojon dehahe hesno jardepu efeteb av ok idu zugaije hezhir ofotohdi betpoz urheeh bakhowup ju. Ocodet nepmi racoec vowuvuzo kubneha ihawucuk mefbaw tutuduc ragi if epe zo uz vafviwtep du gugbulsuz igwa. Mi uwa haz cu ilzib to je nitwuwed useri alfuwzod gor jioza mofkujli us."
  },
  "apiKey": "8bf6532d56cb1233ed8974d58d18bbb24319c0676e61c2023e7509ed46942106",
  "currency": {
    "code": "GYD",
    "name": "Guyana Dollar"
  }
}