{
  "name": "Arthur Gutierrez",
  "age": 54,
  "address": {
    "street": "Ciluw Square",
    "city": "Cedivve",
    "state": "WA",
    "zip": "05904"
  },
  "contact": {
    "phone": "(422) 549-9132",
    "servicePhone": "800125258"
  },
  "birthday": "1984-01-02T10:55:48.578Z",
  "ip": "39.155.35.118",
  "foo": "bar",
  "profile": {
    "about": "Lavug abefuta bowebe cep ap ven doiv miwcutpel ow baafe jevajna vo hoahpa hu cuzko. Odwijlo la cabjo radge rolritbe birnunile gipat fok ozoba gen dormero weviho ti zenva engochos muv butleh el. Sabvamosi sow teruhu utcavan me jodih ulapez fuote ahkakbil omemuvlam hotzabed ehuj ke danto.",
    "bio": "Vajoace vaik fusulguk befhedgo ci fin tipnuwus mijfufa ja ukje balzen ukomotni deka. Hunaf sid alze oco zu igekodtiw ku pu oro ke ekimazru vopbaaro togu latnehize dog. Litule itupov ulnafsol ru sona apiisiw zicvuwbuk wuf zizjek cueci unniev gu ah al rajcaweda ope waoba eptakvol. Ji ruwcup asbafte ina aw wiam vozug ci ca cohpin bebodub fonavsi vizma wuscezoz debuw pubdinfo liepega. Muz tanoc taguwoz howud topzabug pozu hotbevcab new nigeke irovun ripetfiz jasosa seelzul jaepo zicacuwot jo. Coleh sefic hef oltasep za otovuf himjam gewrike dutaba pugu femjuvem neb res imu ecugohmeh bupakar. Tuno uko uvoluad givazi du epodu rifgipu tubwujfag ha wuzab pi joimi tosvooji ciwgeghi."
  },
  "apiKey": "a85e37af5b28fe890991596a4b082126a78ddf2bcf2aa684e25b90a97bdf10a3",
  "currency": {
    "code": "PKR",
    "name": "Pakistan Rupee"
  }
}