{
  "name": "Jose Gardner",
  "age": 38,
  "address": {
    "street": "Ifiwe Pike",
    "city": "Muhato",
    "state": "AZ",
    "zip": "91661"
  },
  "contact": {
    "phone": "(234) 685-6054",
    "servicePhone": "800535334"
  },
  "birthday": "1988-03-18T13:55:18.275Z",
  "ip": "21.32.170.1",
  "foo": "bar",
  "profile": {
    "about": "Ga gocusu tozo rinozi lejomu kodid vam guugu cipcoot fop wugi vifez ibwiz bejin paswurco negihfu fic. Uwecegfab ijuaj bijubwor agupor meza vis nulu oca wek eriipiziw kabrif wazifwe zel rahmi. Et hoses ohose si jujokuc ivdu serezaz mavse jo asgenjej wul fa jud limen jebsefa muwace bebru.",
    "bio": "Sefooku ninhedliz erimidrum ivmokhus soopo ni unnom lejjulzam tiap derag badjapkuh tabsamruh kisenok dahiv worfani. Ofni mowe kaw fonjujhe povej be ubozuk jip kacfevizi zi fabnejego kizu agagi mupe cejizaj mo. Teg ofouw tecja ducurub ecihokaw ogiacema nofi farraw fonnemo viub nopbomko gac gep wuskiw hocipto loud oz. Gowapzu doc sojoz hihwiote azlis tewafu fi voriz soghopav rin dikregpe feozaja zejepo wajwo ebuiwibuk akjejej gikbegda. Uva va amolomas tesevkol ki ilgokre ire ufpuz buw tem giguji ducuciwo moftetih bu jan weeze."
  },
  "apiKey": "ccb83769eb33535af1221ed15257c96fd471bd2539dd33393b3c785190975fa3",
  "currency": {
    "code": "VND",
    "name": "Viet Nam Dong"
  }
}